github_contrib_view/__init__.py
github_contrib_view/config.py
github_contrib_view/constants.py
github_contrib_view/contrib.py
github_contrib_view/main.py
github_contrib_view/output.py
github_contrib_view/structures.py
github_contrib_view-0.3.1.dist-info/WHEEL
github_contrib_view-0.3.1.dist-info/entry_points.txt
github_contrib_view-0.3.1.dist-info/METADATA
github_contrib_view-0.3.1.dist-info/RECORD
